setup.cfg
setup.py
bottlecap/__init__.py
bottlecap/mediatype.py
bottlecap/negotiation.py
bottlecap.egg-info/PKG-INFO
bottlecap.egg-info/SOURCES.txt
bottlecap.egg-info/dependency_links.txt
bottlecap.egg-info/requires.txt
bottlecap.egg-info/top_level.txt