Metadata-Version: 1.1
Name: bottlecap
Version: 0.8.0
Summary: Extras for Bottle
Home-page: https://github.com/imsofly/bottlecap
Author: Cal Leeming
Author-email: cal@iops.io
License: UNKNOWN
Keywords: bottle,bottlecap
Platform: UNKNOWN
Classifier: Programming Language :: Python :: 2.7
Classifier: Programming Language :: Python :: 3.4
